setup.py
winrar/__init__.py
winrar.egg-info/PKG-INFO
winrar.egg-info/SOURCES.txt
winrar.egg-info/dependency_links.txt
winrar.egg-info/top_level.txt